lykkellemainSAmerica/__init__.py
lykkellemainSAmerica/healthcheck6.py
lykkellemainSAmerica/maincalculationprogeod6.py
lykkellemainSAmerica/mainmasterprogeod6.py
lykkellemainSAmerica-0.1.2.dist-info/LICENSE
lykkellemainSAmerica-0.1.2.dist-info/METADATA
lykkellemainSAmerica-0.1.2.dist-info/WHEEL
lykkellemainSAmerica-0.1.2.dist-info/top_level.txt
lykkellemainSAmerica-0.1.2.dist-info/RECORD
